LICENSE
MANIFEST.in
README.rst
setup.py
assetadapter/__init__.py
assetadapter/admin.py
assetadapter/apps.py
assetadapter/models.py
assetadapter/serializers.py
assetadapter/tasks.py
assetadapter/tests.py
assetadapter/urls.py
assetadapter/version.py
assetadapter/views.py
assetadapter/visualizers.py
assetadapter/migrations/0001_initial.py
assetadapter/migrations/__init__.py
assetadapter/templates/assetadapter/base.html
assetadapter/templates/assetadapter/console.html
assetadapter/templates/assetadapter/detail.html
assetadapter/templates/assetadapter/index.html
hedgehog_field_agent.egg-info/PKG-INFO
hedgehog_field_agent.egg-info/SOURCES.txt
hedgehog_field_agent.egg-info/dependency_links.txt
hedgehog_field_agent.egg-info/requires.txt
hedgehog_field_agent.egg-info/top_level.txt
orchestrator/__init__.py
orchestrator/celeryapp.py
orchestrator/config.py
orchestrator/config.server.py
orchestrator/settings.py
orchestrator/urls.py
orchestrator/version.py
orchestrator/wsgi.py
processengine/__init__.py
processengine/admin.py
processengine/apps.py
processengine/flows.py
processengine/forms.py
processengine/models.py
processengine/serializers.py
processengine/tasks.py
processengine/tests.py
processengine/urls.py
processengine/version.py
processengine/views.py
processengine/migrations/0001_initial.py
processengine/migrations/__init__.py
processengine/templates/processengine/parameters.html
processengine/templates/processengine/predefined-parameters.html
processengine/templates/processengine/task-results.html
rmd/__init__.py
rmd/admin.py
rmd/apps.py
rmd/models.py
rmd/tests.py
rmd/urls.py
rmd/version.py
rmd/views.py
rmd/migrations/__init__.py
rmd/templates/rmd/about.html
rmd/templates/rmd/base.html
visacore/__init__.py
visacore/core.py
visaweb/__init__.py
visaweb/admin.py
visaweb/apps.py
visaweb/models.py
visaweb/tests.py
visaweb/urls.py
visaweb/version.py
visaweb/views.py
visaweb/management/__init__.py
visaweb/management/commands/__init__.py
visaweb/management/commands/packagepolymer.py
visaweb/migrations/__init__.py
visaweb/static/visaweb/bower.json
visaweb/static/visaweb/index.html
visaweb/static/visaweb/manifest.json
visaweb/static/visaweb/service-worker.js
