Metadata-Version: 1.1
Name: hedgehog-field-agent
Version: 4.7.1
Summary: Hedgehog station controller.
Home-page: https://github.com/lordoftheflies/hedgehog-station-controller/
Author: lordoftheflies
Author-email: laszlo.hegedus@cherubits.hu
License: Apache 2.0 License
Platform: UNKNOWN
Classifier: Environment :: Web Environment
Classifier: Framework :: Django
Classifier: Framework :: Django :: 1.10
Classifier: Intended Audience :: Developers
Classifier: License :: OSI Approved :: BSD License
Classifier: Operating System :: OS Independent
Classifier: Programming Language :: Python
Classifier: Programming Language :: Python :: 2.7
Classifier: Topic :: Internet :: WWW/HTTP
Classifier: Topic :: Internet :: WWW/HTTP :: Dynamic Content
Classifier: Topic :: Database
Classifier: Topic :: Scientific/Engineering
Classifier: Topic :: Scientific/Engineering :: Information Analysis
Classifier: Topic :: Scientific/Engineering :: Visualization
Classifier: Topic :: System :: Monitoring
Classifier: Development Status :: 2 - Pre-Alpha
